AI_ML/__init__.py
AI_ML/a_star_algorithm.py
AI_ML/alpha_beta_pruning.py
AI_ML/ao_star_algorithm.py
AI_ML/breadth_first_search.py
AI_ML/check_prime.py
AI_ML/classification_algorithms.py
AI_ML/depth_first_search.py
AI_ML/factorial.py
AI_ML/genetic_algorithm.py
AI_ML/hill_climbing.py
AI_ML/iterative_deepening_search.py
AI_ML/makefile.py
AI_ML/min_max_game.py
AI_ML/multiplication_table.py
AI_ML/neural_network.py
AI_ML/simple_calculator.py
AI_ML/simple_chatbot.py
AI_ML/text_to_speech.py
AI_ML/tic_tac_toe.py
AI_ML/traveling_salesperson_problem.py
AI_ML/uniform_cost_search.py
AI_ML/water_jug_problem.py
C/__init__.py
C/createfiles.py
Data_Mining/Makefile.py
Data_Mining/__init__.py
Data_Mining/binary_logistic_regression.py
Data_Mining/data_exploration.py
Data_Mining/data_preprocessing.py
Data_Mining/data_reduction.py
Data_Mining/data_visualization.py
Data_Mining/decision_tree.py
Data_Mining/frequent_itemset_mining.py
Data_Mining/hierarchical_clustering.py
Data_Mining/k_means_clustering.py
Data_Mining/knn_classification.py
Data_Mining/linear_regression.py
Data_Mining/naive_bayes_classification.py
Data_Mining/normalization.py
Data_Mining/social_network_analysis.py
Data_Mining/standardization.py
Java_Programs/__init__.py
Java_Programs/makefile.py
Python_lib/__init__.py
Common_functions-0.1.0.dist-info/LICENSE
Common_functions-0.1.0.dist-info/METADATA
Common_functions-0.1.0.dist-info/WHEEL
Common_functions-0.1.0.dist-info/top_level.txt
Common_functions-0.1.0.dist-info/RECORD
