Metadata-Version: 2.1
Name: Common_functions
Version: 0.1.0
Summary: Mini Project on creating a library for all the program in 5 syllabus
Home-page: https://github.com/Jyotijaladi/Common_functions
Author: Jyoti
Classifier: Programming Language :: Python :: 3
Classifier: License :: OSI Approved :: MIT License
Classifier: Operating System :: OS Independent
Requires: pandas
Requires: numpy
Requires: ctypes
Requires: sklearn
Requires: playsound
Requires: gtts
Requires: torch
License-File: LICENSE
